Workbook

Sheet BD目标
C4: 目标 | D4: 实际完成保费 | E4: 完成率 | F4: 短险ROI | G4: 合计ROI | H4: 税后消费 | I4: 短险佣金 | J4: 支付件均 | K4: 领险成本 | L4: 支付成本 | M4: 转险率 | N4: 总CVR | O4: 拉新率 | P4: 退保率 | Q4: 取代率 | R4: 时间进度 | S4: 日均需完成 | T4: 支付单量 | U4: 支付人数 | V4: 拉新人数 | W4: 退保量 | X4: 取代人数 | Y4: 领险人数 | Z4: 赠险成本 | AA4: UV | AB4: 长险ROI | AC4: 长险佣金
B5: 变现款 | C5: 90000000 | D5: 58184516 | E5: 0.64649462 | F5: 1.6569694 | G5: 1.7868955 | H5: 7637863.2 | I5: 12655705 | J5: 904.66627 | K5: 0 | L5: 118.75526 | M5: 0 | N5: 0.011095946 | O5: 0.79469895 | P5: 0.008225014 | Q5: 0.035916413 | R5: 27 | S5: 7953871 | T5: 20138 | U5: 19101 | V5: 15375 | W5: 137 | X5: 645 | Y5: - | Z5: - | AA5: 1148044 | AB5: 0.15267814 | AC5: 315261.63
B6: 引流款 | C6: 6000000 | D6: 4420020 | E6: 0.73667 | F6: 1.3848481 | G6: 1.8019276 | H6: 631379.25 | I6: 884446 | J6: 824.32301 | K6: 6.6598376 | L6: 117.7507 | M6: 0.056558795 | N6: 0.0030948119 | O6: 0.80719397 | P6: 0.011749347 | Q6: 0.06695263 | R6: 27 | S6: 394995 | T6: 479 | U6: 464 | V6: 411 | W6: 7 | X6: 28 | Y6: 13345 | Z6: 1300 | AA6: 178484 | AB6: 0.34077747 | AC6: 29654.231
B7: 总计 | C7: 96000000 | D7: 62604536 | E7: 0.65213058 | F7: 1.6359711 | G7: 1.7876886 | H7: 8269242.5 | I7: 13540151 | J7: 898.48354 | K7: 6.6598376 | L7: 118.67795 | M7: - | N7: 0.009254704 | O7: 0.79567584 | P7: 0.0084962255 | Q7: 0.038304773 | R7: 0.9 | S7: 8348866 | T7: 20617 | U7: 19565 | V7: 15786 | W7: 144 | X7: 673 | Y7: 13345 | Z7: 1300 | AA7: 1326528 | AB7: 0.16028458 | AC7: 344915.86

Sheet 周例会短险分渠道
A1: 周 | B1: 新元互动 | C1: 上海厚数 | D1: 数鸣信息 | E1: 王炸科技 | F1: 广州安如山 | G1: 巨灿科技 | H1: 新元-腾讯云 | I1: 瑞小云 | J1: 瑞鹏 | K1: 总计
A2: 10.09-10.15 | B2: 12319442 | C2: 433969 | D2: 8974314 | E2: 2461461 | F2: 1401 | G2: 4175174 | H2: 56154 | I2: 2841062 | K2: =SUM(B2:H2) -> 28421915
A3: 10,16-10.22 | B3: 10123861 | C3: 207377 | D3: 7052131 | E3: 1156821 | F3: 11227 | G3: 3786820 | H3: 52084 | I3: 1899495 | K3: =SUM(B3:H3) -> 22390321
A4: 10.23-10.29 | B4: 12370541 | C4: 37150 | D4: 5174368 | E4: 925620 | F4: 3697 | G4: 3152072 | H4: 56901 | I4: 1480980 | K4: =SUM(B4:H4) -> 21720349
A5: 10.30-11.05 | B5: 8863345 | C5: 504353 | D5: 4310443 | E5: 654954 | F5: 190737 | G5: 2166809 | H5: 46466 | I5: 219730 | K5: =SUM(B5:H5) -> 16737107
A6: 11.06-11.12 | B6: 9115407 | C6: 65607 | D6: 4255408 | E6: 605048 | F6: 1641285 | G6: 993577 | H6: 34700 | I6: 31529 | K6: =SUM(B6:H6) -> 16711032
A7: 11.13-11.19 | B7: 6562522 | C7: 92968 | D7: 3400183 | E7: 695201 | F7: 1120957 | G7: 439304 | H7: 83609 | I7: 23318 | K7: =SUM(B7:H7) -> 12394744
A8: 11.20-11.26 | B8: 4656381 | C8: 46623 | D8: 2648248 | E8: 500720 | F8: 614885 | G8: 273339 | H8: 30898 | I8: 67431 | J8: 2633 | K8: =SUM(B8:J8) -> 8841158
A9: 11.27-12.03 | B9: 6867300 | C9: 1402323 | D9: 3016144 | E9: 484469 | F9: 318858 | G9: 50701 | H9: 6137 | I9: 181062 | J9: 51327 | K9: =SUM(B9:J9) -> 12378321
A10: 12.04-12.10 | B10: 7097070 | C10: 4668802 | D10: 3888470 | E10: 521096 | F10: 1667595 | G10: 60452 | H10: 4747 | I10: 17685 | J10: 52326 | K10: =SUM(B10:J10) -> 17978243
A11: 12.11-12.17 | B11: 6107815 | C11: 5993326 | D11: 4034341 | E11: 454374 | F11: 82674 | G11: 16490 | H11: 10678 | I11: 9075 | J11: 99698 | K11: =SUM(B11:J11) -> 16808471
A12: 12.18-12.24 | B12: 5126551 | C12: 3852937 | D12: 3662576 | E12: 401487 | F12: 188095 | G12: 80929 | H12: 385 | I12: 3882 | J12: 76238 | K12: =SUM(B12:J12) -> 13393080
A13: 环比 | B13: =B12/B11-1 -> -0.16065713 | C13: =C12/C11-1 -> -0.35712875 | D13: =D12/D11-1 -> -0.092150118 | E13: =E12/E11-1 -> -0.1163953 | F13: =F12/F11-1 -> 1.2751409 | G13: =G12/G11-1 -> 3.9077623 | H13: =H12/H11-1 -> -0.96394456 | I13: =I12/I11-1 -> -0.5722314 | ... K13: =K12/K11-1 -> -0.20319463
A18: 二级渠道 | B18: 类型 | C18: 渠道标识 | D18: 税后消耗 | E18: 渠道规模保费 | F18: 短险ROI | G18: 长险ROI | H18: 综合ROI | I18: 件均 | J18: 拉新率 | K18: 退保率 | L18: 取代率 | M18: 保费占比 | N18: 新用户数 | O18: 成单单量 | P18: 退单量 | Q18: 成单人数 | R18: 取代人数 | S18: 佣金收入 | U18: 0.21
A19: 新元互动 | B19: 智能短信类 | C19: BD_XYdx | D19: 344806.6 | E19: 5126551 | F19: =S19/D19 -> 3.3155423 | G19: =VLOOKUP(C19,[1]长险价值!$B:$K,10,0) -> 0.215728 | H19: =F19+G19 -> 3.5312703 | I19: =E19/Q19 -> 938.58495 | J19: =N19/Q19 -> 0.72592457 | K19: =P19/O19 -> 0.010643777 | L19: =R19/Q19 -> 0.040278286 | M19: =E19/$E$27 -> 0.38278711 | N19: 3965 | O19: 5825 | P19: 62 | Q19: 5462 | R19: 220 | S19: 1143220.9
A20: 数鸣信息 | B20: 营销短信类 | C20: BD_SMdx | D20: 749547.17 | E20: 3662576 | F20: =S20/D20 -> 1.0896638 | G20: =VLOOKUP(C20,[1]长险价值!$B:$K,10,0) -> 0.11603682 | H20: =F20+G20 -> 1.2057007 | I20: =E20/Q20 -> 851.56382 | J20: =N20/Q20 -> 0.83678214 | K20: =P20/O20 -> 0.0077279753 | L20: =R20/Q20 -> 0.044175773 | M20: =E20/$E$27 -> 0.27347565 | N20: 3599 | O20: 4529 | P20: 35 | Q20: 4301 | R20: 190 | S20: 816754.45
A21: 上海厚数 | B21: 营销短信类 | C21: BD_WCJW | D21: 670754.72 | E21: 3852937 | F21: =S21/D21 -> 1.2809525 | G21: =VLOOKUP(C21,[1]长险价值!$B:$K,10,0) -> 0.10294108 | H21: =F21+G21 -> 1.3838936 | I21: =E21/Q21 -> 1002.0642 | J21: =N21/Q21 -> 0.84421326 | K21: =P21/O21 -> 0.009923096 | L21: =R21/Q21 -> 0.035630689 | M21: =E21/$E$27 -> 0.28768945 | N21: 3246 | O21: 4031 | P21: 40 | Q21: 3845 | R21: 137 | S21: 859204.95
A22: 王炸科技 | B22: 营销短信类 | C22: BD_WZKJ | D22: 72245.283 | E22: 401487 | F22: =S22/D22 -> 1.2392726 | G22: =VLOOKUP(C22,[1]长险价值!$B:$K,10,0) -> 0.13812033 | H22: =F22+G22 -> 1.3773929 | I22: =E22/Q22 -> 753.25891 | J22: =N22/Q22 -> 0.83302064 | K22: =P22/O22 -> 0.0054054054 | L22: =R22/Q22 -> 0.039399625 | M22: =E22/$E$27 -> 0.029978059 | N22: 444 | O22: 555 | P22: 3 | Q22: 533 | R22: 21 | S22: 89531.601
A23: 菲克 | B23: 营销短信类 | C23: BD_FKdx | D23: 27811.321 | E23: 188095 | F23: =S23/D23 -> 1.5082054 | G23: =VLOOKUP(C23,[1]长险价值!$B:$K,10,0) -> 0 | H23: =F23+G23 -> 1.5082054 | I23: =E23/Q23 -> 895.69048 | J23: =N23/Q23 -> 0.8 | K23: =P23/O23 -> 0.0046296296 | L23: =R23/Q23 -> 0.0095238095 | M23: =E23/$E$27 -> 0.014044597 | N23: 168 | O23: 216 | P23: 1 | Q23: 210 | R23: 2 | S23: 41945.185
A24: 瑞小云 | B24: 营销短信类 | C24: BD_RYdx | D24: 613.20755 | E24: 3882 | F24: =S24/D24 -> 1.4117341 | G24: =VLOOKUP(C24,[1]长险价值!$B:$K,10,0) -> 0.076581729 | H24: =F24+G24 -> 1.4883158 | I24: =E24/Q24 -> 776.4 | J24: =N24/Q24 -> 0.2 | K24: =P24/O24 -> 0 | L24: =R24/Q24 -> 0 | M24: =E24/$E$27 -> 0.00028985951 | N24: 1 | O24: 5 | P24: 0 | Q24: 5 | R24: 0 | S24: 865.686
A25: 瑞鹏 | B25: 营销短信类 | C25: BD_RPKJ | D25: 12141.509 | E25: 76238 | F25: =S25/D25 -> 1.4002439 | G25: =VLOOKUP(C25,[1]长险价值!$B:$K,10,0) -> 0.094316228 | H25: =F25+G25 -> 1.4945601 | I25: =E25/Q25 -> 785.95876 | J25: =N25/Q25 -> 0.81443299 | K25: =P25/O25 -> 0 | L25: =R25/Q25 -> 0.082474227 | M25: =E25/$E$27 -> 0.0056925063 | N25: 79 | O25: 100 | P25: 0 | Q25: 97 | R25: 8 | S25: 17001.074
A26: 巨灿 | B26: 营销短信类 | C26: BD_JCdx | D26: 12150.943 | E26: 80929 | F26: =S26/D26 -> 1.4852482 | G26: =VLOOKUP(C26,[1]长险价值!$B:$K,10,0) -> 0.21024465 | H26: =F26+G26 -> 1.6954929 | I26: =E26/Q26 -> 909.31461 | J26: =N26/Q26 -> 0.8988764 | K26: =P26/O26 -> 0 | L26: =R26/Q26 -> 0.02247191 | M26: =E26/$E$27 -> 0.0060427718 | N26: 80 | O26: 94 | P26: 0 | Q26: 89 | R26: 2 | S26: 18047.167
A27: 合计 | B27: 合计 | D27: =SUM(D19:D26) -> 1890070.8 | E27: =SUM(E19:E26) -> 13392695 | F27: =S27/D27 -> 1.5801371 | G27: 0.12899713 | H27: =F27+G27 -> 1.7091343 | I27: =E27/Q27 -> 920.96651 | J27: =N27/Q27 -> 0.79645166 | K27: =P27/O27 -> 0.0091826767 | L27: =R27/Q27 -> 0.039884473 | M27: =E27/$E$27 -> 1 | N27: =SUM(N19:N26) -> 11582 | O27: =SUM(O19:O26) -> 15355 | P27: =SUM(P19:P26) -> 141 | Q27: =SUM(Q19:Q26) -> 14542 | R27: =SUM(R19:R26) -> 580 | S27: =SUM(S19:S26) -> 2986571
A30: 撞库进度
A31: 渠道 | B31: 是否可撞库 | C31: 11月保费（占比） | D31: 投放状态 | E31: 保费空间 | F31: 接入状态 | G31: 原因
A32: 数鸣 | B32: 是 | C32: 1500万（26%） | D32: 在投 | E32: 1500-3000万 | F32: 对接完成 | G32: ——
A33: 王炸 | B33: 是 | C33: 260万（4%） | D33: 在投 | E33: 500万-800万 | F33: 对接完成 | G33: ——
A34: 瑞小云 | B34: 是 | C34: 30万（0.5%） | D34: 重启测试 | E34: 500万-1000万 | F34: 对接完成 | G34: ——
A35: 瑞鹏 | B35: 是 | C35: - | D35: 重启测试 | E35: 500万-1000万 | F35: 对接完成 | G35: ——
A36: 厚数 | B36: 否 | C36: 90万（2%） | D36: 重启测试 | E36: 1500-3000万 | F36: 进入对接流程 | G36: 合规及数据安全问题
A37: 巨灿 | B37: 否 | C37: 300万（5%） | D37: 在投 | E37: 500-1500万 | G37: 可出库数据为设备号
A38: 菲克 | B38: 否 | C38: 370万（7%） | D38: 测试 | E38: 500万 | G38: 运营商数据无法出库
A41: 渠道 | B41: 点击率 | C41: 文案
A42: 数鸣（老） | B42: 0.0088677779 | C42: 【水滴保】尾号XXXX用户，您的600万医疗保额消息已送达，请尽快查看，点击 http://z0k.cn/Fn434 过期失效，退订回T
A43: 数鸣（新） | B43: 0.011255282 | C43: 【水滴保】审核通过：您XXXX账户600万医疗保障服务已成功到账！请24点前查看 http://z0k.cn/KZzVu 退订回T
A44: 0.26923366
A45: 瑞鹏（老） | B45: 0.0077 | C45: 【水滴保】尾号1234的用户，您的600万保额医疗险通知已成功送达，请于1小时内点击，戳XXX，退订回T
A46: 瑞鹏（新） | B46: 0.0122 | C46: 【水滴保】入账通知：账户1234已成功到账最高600万健康保障，请于24:00前确认，详情XXXX，回N取关
A47: 0.58441558

Sheet 周例会赠险分渠道
A1: 周 | B1: 同盾 | C1: 远山保 | D1: 金数据 | E1: 上量 | F1: 极光数据 | G1: 新旦 | H1: 新元 | I1: 总计
A2: 10.09-10.15 | B2: 1562954 | C2: 1253559 | D2: 63955 | E2: 125833 | F2: 4873 | G2: 69693 | I2: =SUM(B2:G2) -> 3080867
A3: 10,16-10.22 | B3: 339751 | C3: 623025 | D3: 63841 | E3: 76786 | F3: 0 | G3: 17540 | I3: =SUM(B3:G3) -> 1120943
A4: 10.23-10.29 | B4: 316857 | C4: 483061 | D4: 57981 | E4: 106224 | F4: 2664 | G4: 47685 | I4: =SUM(B4:G4) -> 1014472
A5: 10.30-11.05 | B5: 52961 | C5: 223165 | D5: 53512 | E5: 68988 | F5: 43108 | G5: 11884 | I5: =SUM(B5:G5) -> 453618
A6: 11.06-11.12 | B6: 143257 | C6: 55867 | D6: 52185 | E6: 40984 | F6: 21677 | G6: 4256 | H6: - | I6: =SUM(B6:G6) -> 318226
A7: 11.13-11.19 | B7: 181764 | C7: 114307 | D7: 39038 | E7: 46919 | F7: 52833 | G7: 13235 | H7: - | I7: =SUM(B7:G7) -> 448096
A8: 11.20-11.26 | B8: 230330 | C8: 173154 | D8: 74712 | E8: 44655 | F8: 214154 | G8: 21687 | H8: - | I8: =SUM(B8:G8) -> 758692
A9: 11.28-12.04 | B9: 155250 | C9: 110415 | D9: 90167 | E9: 49971 | F9: 199947 | G9: 12426 | H9: - | I9: =SUM(B9:G9) -> 618176
A10: 12.04-12.10 | B10: 46726 | C10: 132169 | D10: 69848 | E10: 49838 | F10: 204458 | G10: 69213 | H10: 214781 | I10: =SUM(B10:H10) -> 787033
A11: 12.11-12.17 | B11: 63984 | C11: 145847 | D11: 57517 | E11: 26127 | F11: 257301 | G11: 199027 | H11: 581852 | I11: =SUM(B11:H11) -> 1331655
A12: 12.18-12.24 | B12: 334500 | C12: 91190 | D12: 71607 | E12: 25649 | F12: 330252 | G12: 89829 | H12: 666918 | I12: =SUM(B12:H12) -> 1609945
A13: 环比 | B13: =B12/B11-1 -> 4.2278695 | C13: =C12/C11-1 -> -0.37475574 | D13: =D12/D11-1 -> 0.24497105 | E13: =E12/E11-1 -> -0.01829525 | F13: =F12/F11-1 -> 0.28352397 | G13: =G12/G11-1 -> -0.54865923 | H13: =H12/H11-1 -> 0.14619869 | I13: =I12/I11-1 -> 0.20898055
A18: 渠道 | B18: 类型 | C18: 渠道号 | D18: 税后消耗 | E18: 渠道规模保费 | F18: 短险收益ROI | G18: 长险收益ROI | H18: 综合收益ROI | I18: 支付成本 | J18: 转险率 | K18: 拉新率 | L18: 退保率 | M18: 取消代扣 | N18: 占比 | O18: 佣金收入 | P18: 领险人数 | Q18: 成单人数 | R18: 新用户数 | S18: 退保单量 | T18: 取代人数 | U18: 赠险成本
A19: 同盾 | B19: 代理类 | C19: BD_TDzx | D19: 76202.83 | E19: 334500 | F19: =O19/(D19+U19) -> 0.86829997 | G19: 0.2131714 | H19: =F19+G19 -> 1.0814714 | I19: =D19/Q19 -> 180.14853 | J19: =Q19/P19 -> 0.036875599 | K19: =R19/Q19 -> 0.86052009 | L19: =S19/Q19 -> 0.0094562648 | M19: =T19/Q19 -> 0.11111111 | N19: =Q19/$Q$26 -> 0.22926829 | O19: 66933.45 | P19: 11471 | Q19: 423 | R19: 364 | S19: 4 | T19: 47 | U19: 882.8
A20: 远山保 | B20: 代理类 | C20: BD_YSBzx | D20: 31797.17 | E20: 91190 | F20: =O20/(D20+U20) -> 0.57358277 | G20: 0.2131714 | H20: =F20+G20 -> 0.78675417 | I20: =D20/Q20 -> 225.51184 | J20: =Q20/P20 -> 0.030712263 | K20: =R20/Q20 -> 0.85815603 | L20: =S20/Q20 -> 0.014184397 | M20: =T20/Q20 -> 0.070921986 | N20: =Q20/$Q$26 -> 0.076422764 | O20: 18247.119 | P20: 4591 | Q20: 141 | R20: 121 | S20: 2 | T20: 10 | U20: 15.36
A21: 金数据 | B21: 问卷类 | C21: BD_JSJzx | D21: 14625 | E21: 71607 | F21: =O21/(D21+U21) -> 0.97973065 | G21: 0.2131714 | H21: =F21+G21 -> 1.192902 | I21: =D21/Q21 -> 176.20482 | J21: =Q21/P21 -> 0.038676608 | K21: =R21/Q21 -> 0.73493976 | L21: =S21/Q21 -> 0.012048193 | M21: =T21/Q21 -> 0.012048193 | N21: =Q21/$Q$26 -> 0.04498645 | O21: 14328.561 | P21: 2146 | Q21: 83 | R21: 61 | S21: 1 | T21: 1 | U21: 0
A22: 上量 | B22: 快消扫码类 | C22: BD_SLzx | D22: 6665.0943 | E22: 25649 | F22: =O22/(D22+U22) -> 0.72551547 | G22: =VLOOKUP(C20,[2]长险价值!$B:$L,11,0) -> 0.3011034 | H22: =F22+G22 -> 1.0266189 | I22: =D22/Q22 -> 190.43127 | J22: =Q22/P22 -> 0.036997886 | K22: =R22/Q22 -> 0.97142857 | L22: =S22/Q22 -> 0.028571429 | M22: =T22/Q22 -> 0.057142857 | N22: =Q22/$Q$26 -> 0.01897019 | O22: 5132.3649 | P22: 946 | Q22: 35 | R22: 34 | S22: 1 | T22: 2 | U22: 409
A23: 极光 | B23: 小程序 | C23: BD_SHJGzx | D23: 57566.038 | E23: 330252 | F23: =O23/(D23+U23) -> 1.1479585 | G23: =VLOOKUP(C19,[2]长险价值!$B:$L,11,0) -> 0.32972885 | H23: =F23+G23 -> 1.4776874 | I23: =D23/Q23 -> 130.2399 | J23: =Q23/P23 -> 0.062253521 | K23: =R23/Q23 -> 0.7918552 | L23: =S23/Q23 -> 0.0067873303 | M23: =T23/Q23 -> 0.045248869 | N23: =Q23/$Q$26 -> 0.2395664 | O23: 66083.425 | P23: 7100 | Q23: 442 | R23: 350 | S23: 3 | T23: 20 | U23: 0
A24: 新旦 | B24: 代理类 | C24: BD_XDzx | D24: 13507.075 | E24: 89829 | F24: =O24/(D24+U24) -> 1.2727695 | G24: 0.2131714 | H24: =F24+G24 -> 1.4859409 | I24: =D24/Q24 -> 112.55896 | J24: =Q24/P24 -> 0.062565172 | K24: =R24/Q24 -> 0.83333333 | L24: =S24/Q24 -> 0 | M24: =T24/Q24 -> 0.15 | N24: =Q24/$Q$26 -> 0.06504065 | O24: 17974.783 | P24: 1918 | Q24: 120 | R24: 100 | S24: 0 | T24: 18 | U24: 615.5
A25: 新元 | B25: 智能短信 | C25: BD_XYzx | D25: 13875 | E25: 666918 | F25: =O25/(D25+U25) -> 9.618039 | G25: 0.2131714 | H25: =F25+G25 -> 9.8312104 | I25: =D25/Q25 -> 23.086522 | J25: =Q25/P25 -> 0.11941188 | K25: =R25/Q25 -> 0.72712146 | L25: =S25/Q25 -> 0.0083194676 | M25: =T25/Q25 -> 0.036605657 | N25: =Q25/$Q$26 -> 0.32574526 | O25: 133450.29 | P25: 5033 | Q25: 601 | R25: 437 | S25: 5 | T25: 22 | U25: 0
A26: 总计 | D26: =SUM(D19:D25) -> 214238.21 | E26: =SUM(E19:E25) -> 1609945 | F26: =O26/(D26+U26) -> 1.4903252 | G26: 0.2131714 | H26: =F26+G26 -> 1.7034966 | I26: =D26/Q26 -> 116.11827 | J26: =Q26/P26 -> 0.055563921 | K26: =R26/Q26 -> 0.79512195 | L26: =S26/Q26 -> 0.0086720867 | M26: =T26/Q26 -> 0.06504065 | N26: =Q26/$Q$26 -> 1 | O26: =SUM(O19:O25) -> 322149.99 | P26: =SUM(P19:P25) -> 33205 | Q26: =SUM(Q19:Q25) -> 1845 | R26: =SUM(R19:R25) -> 1467 | S26: =SUM(S19:S25) -> 16 | T26: =SUM(T19:T25) -> 120 | U26: =SUM(U19:U25) -> 1922.66
A31: 产品 | B31: 税后消耗 | C31: 渠道规模保费 | D31: 短险收益ROI | E31: 长险收益ROI | F31: 综合收益ROI | G31: 支付成本 | H31: 转险率 | I31: 拉新率 | J31: 退保率 | K31: 取消代扣 | L31: 占比 | M31: 佣金收入 | N31: 领险人数 | O31: 成单人数 | P31: 新用户数 | Q31: 退保单量 | R31: 取代人数 | S31: 赠险成本
A32: 500元重疾险 | B32: 108941.04 | C32: 988688 | D32: =M32/(B32+S32) -> 1.8159958 | E32: 0.2131714 | F32: =D32+E32 -> 2.0291672 | G32: =B32/O32 -> 103.45778 | H32: =O32/N32 -> 0.068487805 | I32: =P32/O32 -> 0.77302944 | J32: =Q32/O32 -> 0.012345679 | K32: =R32/O32 -> 0.051282051 | L32: =O32/$Q$26 -> 0.57073171 | M32: 197836.47 | N32: 15375 | O32: 1053 | P32: 814 | Q32: 13 | R32: 54 | S32: 0
A33: 账户安全险 | B33: 27042.453 | C33: 153246 | D33: =M33/(B33+S33) -> 1.059079 | E33: 0.2131714 | F33: =D33+E33 -> 1.2722504 | G33: =B33/O33 -> 116.06203 | H33: =O33/N33 -> 0.0609469 | I33: =P33/O33 -> 0.87124464 | J33: =Q33/O33 -> 0.021459227 | K33: =R33/O33 -> 0.12875536 | L33: =O33/$Q$26 -> 0.12628726 | M33: 30664.525 | N33: 3823 | O33: 233 | P33: 203 | Q33: 5 | R33: 30 | S33: 1911.5
A34: 权益卡 | B34: 22033.019 | C34: 129425 | D34: =M34/(B34+S34) -> 1.1754151 | E34: 0.2131714 | F34: =D34+E34 -> 1.3885865 | G34: =B34/O34 -> 123.08949 | H34: =O34/N34 -> 0.056413489 | I34: =P34/O34 -> 0.7877095 | J34: =Q34/O34 -> 0.011173184 | K34: =R34/O34 -> 0.10055866 | L34: =O34/$Q$26 -> 0.09701897 | M34: 25897.943 | N34: 3173 | O34: 179 | P34: 141 | Q34: 2 | R34: 18 | S34: 0
A35: 2万重疾送手机 | B35: 14575.472 | C35: 48253 | D35: =M35/(B35+S35) -> 0.66244342 | E35: 0.2131714 | F35: =D35+E35 -> 0.87561482 | G35: =B35/O35 -> 231.35669 | H35: =O35/N35 -> 0.028099911 | I35: =P35/O35 -> 0.88888889 | J35: =Q35/O35 -> 0 | K35: =R35/O35 -> 0.095238095 | L35: =O35/$Q$26 -> 0.034146341 | M35: 9655.4253 | N35: 2242 | O35: 63 | P35: 56 | Q35: 0 | R35: 6 | S35: 0
A36: 异常天气险 | B36: 5865.566 | C36: 7405 | D36: =M36/(B36+S36) -> 0.2526168 | E36: 0.2131714 | F36: =D36+E36 -> 0.4657882 | G36: =B36/O36 -> 586.5566 | H36: =O36/N36 -> 0.011918951 | I36: =P36/O36 -> 1 | J36: =Q36/O36 -> 0 | K36: =R36/O36 -> 0.1 | L36: =O36/$Q$26 -> 0.0054200542 | M36: 1481.7405 | N36: 839 | O36: 10 | P36: 10 | Q36: 0 | R36: 1 | S36: 0
A37: 赠险大礼包 | B37: 4676.8868 | C37: 7109 | D37: =M37/(B37+S37) -> 0.30415765 | E37: 0.2131714 | F37: =D37+E37 -> 0.51732905 | G37: =B37/O37 -> 389.74057 | H37: =O37/N37 -> 0.018018018 | I37: =P37/O37 -> 0.91666667 | J37: =Q37/O37 -> 0 | K37: =R37/O37 -> 0.16666667 | L37: =O37/$Q$26 -> 0.006504065 | M37: 1422.5109 | N37: 666 | O37: 12 | P37: 11 | Q37: 0 | R37: 2 | S37: 0
A38: 总计 | B38: =SUM(B35:B37) -> 25117.925 | C38: =SUM(C35:C37) -> 62767 | D38: =M38/(B38+S38) -> 0.50002844 | E38: 0.2131714 | F38: =D38+E38 -> 0.71319984 | G38: =B38/O38 -> 295.50499 | H38: =O38/N38 -> 0.022684815 | I38: =P38/O38 -> 0.90588235 | J38: =Q38/O38 -> 0 | K38: =R38/O38 -> 0.10588235 | L38: =S38/Q38 -> #DIV/0! | M38: =SUM(M35:M37) -> 12559.677 | N38: =SUM(N35:N37) -> 3747 | O38: =SUM(O35:O37) -> 85 | P38: =SUM(P35:P37) -> 77 | Q38: =SUM(Q35:Q37) -> 0 | R38: =SUM(R35:R37) -> 9 | S38: =SUM(S35:S37) -> 0

Sheet 互动渠道
A1: 周 | B1: 渠道规模保费 | C1: 综合ROI
A2: 11.20-11.26 | B2: 4664294 | C2: 0.85840227
A3: 11.28-12.03 | B3: 2954205 | C3: 0.84920668
A4: 12.04-12.10 | B4: 3657894 | C4: 0.70480022
A5: 12.11-12.17 | B5: 4495100 | C5: 0.72451903
A6: 环比 | B6: =B5/B4-1 -> 0.22887651 | C6: =C5/C4-1 -> 0.027977877
A12: 产品 | B12: 税后消耗 | C12: 渠道规模保费 | D12: 短险ROI | E12: 综合ROI | F12: 件均 | G12: 领险成本 | H12: 支付成本 | I12: 退保取代率 | J12: cpm | K12: cpc | L12: 领险率 | M12: 转险率 | N12: ctr | O12: 总转化率
A13: 100万交通意外险 | B13: 851643.66 | C13: 1861698 | D13: 0.51582655 | E13: 0.71080053 | F13: 782.22605 | G13: 16.189097 | H13: 357.83347 | I13: 0.049159664 | J13: 877.17207 | K13: 1.3132328 | L13: 0.067732931 | M13: 0.045241988 | N13: 0.66794867 | O13: 0.0030643724
A14: 账户安全险 | B14: 714205.97 | C14: 1731989 | D14: 0.56797505 | E14: 0.75435211 | F14: 844.04922 | G14: 17.176258 | H14: 348.05359 | I14: 0.048245614 | J14: 488.61549 | K14: 0.93621703 | L14: 0.045562527 | M14: 0.049349462 | N14: 0.52190408 | O14: 0.0022484862
A15: 赠险送手机 | B15: 233898.41 | C15: 760575 | D15: 0.52027717 | E15: 0.71643538 | F15: 550.3437 | G15: 13.256541 | H15: 169.24631 | I15: 0.22503618 | J15: 155.52837 | K15: 0.77406706 | L15: 0.048748815 | M15: 0.07832691 | N15: 0.20092363 | O15: 0.0038183441
A16: 赠险大礼包 | B16: 45772.383 | C16: 77588 | D16: 0.40109496 | E16: 0.59725318 | F16: 891.81609 | G16: 29.568723 | H16: 526.11934 | I16: 0.034482759 | J16: 408.30337 | K16: 0.8173981 | L16: 0.023078987 | M16: 0.05620155 | N16: 0.49951593 | O16: 0.0012970749
A17: 权益卡 | B17: 32806.52 | C17: 61798 | D17: 0.45731458 | E17: 0.65347279 | F17: 1103.5357 | G17: 44.574076 | H17: 585.83072 | I17: 0.035714286 | J17: 436.47769 | K17: 0.74082631 | L17: 0.013875535 | M17: 0.076086957 | N17: 0.58917682 | O17: 0.0010557472
A18: 异常天气险 | B18: 1018.751 | C18: 1452 | D18: 0.33485509 | E18: 0.5310133 | F18: 484 | G18: 13.404619 | H18: 339.58368 | I18: 0 | J18: 247.86919 | K18: 0.65675996 | L18: 0.040904198 | M18: 0.039473684 | N18: 0.37741215 | O18: 0.0016146394

Sheet 竟品数据
A1: 渠道 | B1: 产品 | C1: 点击率 | D1: 下单率 | E1: 综合转化率（下单/发送成功） | H1: 保司
A2: 瑞鹏 | B2: 水滴-人保 | C2: 0.0063 | D2: 0.0216 | E2: 0.00014 | H2: 悟空保 | I2: 【医疗险】请核对：您的3750账户600万医疗险已到达！请1小时内查看 89dt.cn/hV 过期作废！退订回T
B3: 度小满-人保 | C3: 0.0113 | D3: 0.0276 | E3: 0.000312 | H3: 众安 | I3: 【众安保险】@亲，您的最高600万保额医疗险已送达，请于1小时内查看 https://i.zhongan.com/vLVCLQ 退订回T
B4: 悟空保-泰康 | C4: 0.0095 | D4: 0.0313 | E4: 0.000297 | H4: 悟空保 | I4: 【众安保险】请您核对订单信息：您的2268账户600万保额医疗险已到达！请1小时内查看，XXXX退订回T
B5: 悟空保-华泰 | C5: 0.0085 | D5: 0.0306 | E5: 0.00026 | H5: 泰康 | I5: 【泰康保险】请核对：您的4746账户600万医疗险已到达！请1小时内查看。XXX过期作废！退订回T
B6: 星火保-太平 | C6: 0.0104 | D6: 0.0244 | E6: 0.000254 | H6: 星火保 | I6: 【太平保险】请核对！用户2268您600万医疗险已到达！今天24:00前不领自动作废。戳XXX立即查看！
B7: 众安 | C7: 0.0091 | D7: 0.0144 | E7: 0.000131 | H7: 度小满 | I7: 【中国人保】请您核对信息：您的0726账户600万保额医疗险已到达！请1小时内查看XXXXXX，过期作废，退订回T
A9: 瑞小云 | B9: 度小满-人保 | C9: 0.019491687 | D9: 0.026659586 | E9: 0.00058113545
B10: 360保险 | C10: 0.012796387 | D10: 0.028837316 | E10: 0.00040548971
B11: 水滴-安心 | C11: 0.0104 | D11: 0.0199 | E11: 0.00026
B12: 水滴-太平 | C12: 0.0102 | D12: 0.0251 | E12: 0.00026
A14: 数鸣 | B14: 守护保-大地 | C14: 0.014 | D14: 0.022 | E14: 0.00031
B15: XX保险 | C15: 0.016 | D15: 0.02 | E15: 0.00032
B16: 水滴-安心 | C16: 0.015 | D16: 0.0085 | E16: 0.00013
H17: 水滴 | I17: 【水滴保】您XX账号，最高600万保额消息已成功送达！24点前点击url过期失效， 退订回T
H18: 水滴 | I18: 【水滴保】尾号XX用户，您最高600万保额医疗险消息已于8月23日通知！请立即点击查看过期失效 ，退订回T
H19: 水滴 | I19: 【水滴保】通知，您最高600万保额医疗险消息已于今日送达！请立即点击查看XX过期失效 ，退订回T
H20: 水滴 | I20: 【水滴保】尾号[(B)]用户，您的600万医疗保额消息已送达，请尽快查看，点击XX过期失效，退订回T
H21: 水滴 | I21: 【水滴保】您的保障信息已到：最高600万重疾医疗保障，责任内看病住院可报销，速戳xxx查看。退回复T
H22: 水滴 | I22: 【水滴保】请您查看信息：您的XXXX账户最高600万保额医疗险消息已投递！请1小时内查看url 退订回T
H23: 水滴 | I23: 【水滴保】尾号XX用户，您的600万保额医疗险通知已成功送达，请于1小时内点击，戳 XX 退订回T
H24: 水滴 | I24: 【水滴保】温馨提示，您的最高600万保额医疗险信息已备好，请于24小时内戳XX，退订回T
H25: 水滴 | I25: 【水滴保】您有一份终生保险定制服务待查看，请尽快点击http://9oj.cn/44oB3 退订回T
H26: 水滴 | I26: 【水滴保】通知：您的8201账号已成功到达一份终生保险定制服务信息，戳xxx过期失效，退订回T

Sheet 阶梯单价
A1: 产品 | B1: 定价标准 | D1: 结算方式 | E1: 核减标准 | F1: 预期收益 | G1: 备注
A2: 引流款 | B2: 单价 | C2: 11月阶梯量级 | D2: M+1结算80% M+3结算20% （考核二期续费率80%，三期续费率以当期大盘均值为准：参考值68%-70%） | E2: 核减金额=单价*当月结算单量*（80%-二期续费率+大盘均值-三期续费率） | F2: 预估新增保费1,600万，预估达成7,500万 ，由日均200万提升至300万保费，综合ROI由2.05降低至1.75 | G2: 因政策调整时间已近月中，部分渠道难以追满阶梯，申请从开始投放之日起至月末，日均达到对应阶梯水平，即按对应阶梯单价结算。
B3: 110 | C3: -
B4: 130 | C4: 0-3,000
B5: 140 | C5: 3,001-6,000
B6: 150 | C6: 6,000-10,000
B7: 170 | C7: 10,001-15,000
B8: 180 | C8: 15,000以上
A9: 变现款 | B9: 500元重疾7.5元/CPA 账户安全险7.5元/CPA | D9: 次月结算100%（负向指标正常） | E9: 核减规则：按子渠道维度评估 | F9: 保费日均提升15万，全月增长180万，综合ROI 1.1
E10: 负向指标=当日退保率+当日取代率（参考值8%）
E11: 1） 子渠道当日负向指标≤8%，正常结算
E12: 2）子渠道12%≥当日负向指标＞8%时 ，结算金额=总单量*(1-(负向指标-8%)）*单价 结算；
E13: 3）子渠道当日负向指标＞12%时，该子渠道当月全部数据不予结算。

Sheet 跟进进度
B1: 目前跟进情况（数量）
B2: 行业 | C2: 已沟通 （渠道数） | D2: 暂不考虑合作 | E2: 可跟进 | F2: 待测试/测试中 | G2: 已合作 | U2: 行业 | V2: 已沟通 | W2: 暂不考虑 | X2: 可跟进 | Y2: 待测试/测试中 | Z2: 已合作 | AB2: 行业 | AC2: 合计
B3: 旅游出行 | C3: 21 | D3: =W3/$V$3 -> 0.66666667 | E3: =X3/$V$3 -> 0.33333333 | F3: - | G3: - | U3: 旅游出行 | V3: =C3 -> 21 | W3: 14 | X3: 7 | Y3: - | Z3: - | AB3: 暂不考虑合作 | AC3: =D13 -> 0.61538462
B4: 工具服务 | C4: 13 | D4: =W4/$V$4 -> 0.53846154 | E4: =X4/$V$4 -> 0.38461538 | F4: - | G4: - | U4: 工具服务 | V4: =C4 -> 13 | W4: 7 | X4: 5 | Y4: 1 | Z4: - | AB4: 可跟进 | AC4: =E13 -> 0.30769231
B5: 学习教育 | C5: 7 | D5: =W5/$V$5 -> 0.85714286 | E5: - | G5: - | U5: 学习教育 | V5: =C5 -> 7 | W5: 6 | X5: - | Y5: 1 | Z5: - | AB5: 待测试/测试中 | AC5: =F13 -> 0.061538462
B6: 汽车服务 | C6: 7 | D6: =W6/$V$6 -> 0.57142857 | E6: =X6/$V$6 -> 0.28571429 | F6: - | G6: =Z6/$V$6 -> 0.14285714 | U6: 汽车服务 | V6: =C6 -> 7 | W6: 4 | X6: 2 | Y6: - | Z6: 1 | AB6: 已合作 | AC6: =G13 -> 0.015384615
B7: 电子商务 | C7: 8 | D7: =W7/$V$7 -> 0.5 | E7: =X7/$V$7 -> 0.375 | F7: =Y7/$V$7 -> 0.125 | G7: - | U7: 电子商务 | V7: =C7 -> 8 | W7: 4 | X7: 3 | Y7: 1 | Z7: -
B8: 金融理财 | C8: 2 | D8: =W8/$V$8 -> 0.5 | E8: - | F8: =Y8/$V$8 -> 0.5 | G8: - | U8: 金融理财 | V8: =C8 -> 2 | W8: 1 | X8: - | Y8: 1 | Z8: -
B9: 社交网络 | C9: 2 | D9: =W9/$V$9 -> 1 | E9: - | F9: - | G9: - | U9: 社交网络 | V9: =C9 -> 2 | W9: 2 | X9: - | Y9: - | Z9: -
B10: 医疗健康 | C10: 2 | D10: =W10/$V$10 -> 0.5 | E10: =X10/$V$10 -> 0.5 | F10: - | G10: - | U10: 医疗健康 | V10: =C10 -> 2 | W10: 1 | X10: 1 | Y10: - | Z10: -
B11: 社区服务 | C11: 1 | D11: - | E11: =X11/$V$11 -> 1 | F11: - | G11: - | U11: 社区服务 | V11: =C11 -> 1 | W11: - | X11: 1 | Y11: - | Z11: -
B12: 代理渠道 | C12: 2 | D12: =W12/$V$12 -> 0.5 | E12: =X12/$V$12 -> 0.5 | F12: - | G12: - | U12: 代理渠道 | V12: =C12 -> 2 | W12: 1 | X12: 1 | Y12: - | Z12: -
B13: 合计 | C13: =SUM(C3:C12) -> 65 | D13: =W13/$V$13 -> 0.61538462 | E13: =X13/$V$13 -> 0.30769231 | F13: =Y13/$V$13 -> 0.061538462 | G13: =Z13/$V$13 -> 0.015384615 | U13: 合计 | V13: =SUM(V3:V12) -> 65 | W13: =SUM(W3:W12) -> 40 | X13: =SUM(X3:X12) -> 20 | Y13: =SUM(Y3:Y12) -> 4 | Z13: =SUM(Z3:Z12) -> 1
U16: 不考虑合作 | Y16: 可跟进分类
U18: 原因 | V18: 占比 | W18: 数量 | Y18: 原因 | Z18: 占比 | AA18: 数量
U19: 不接保险类产品 | V19: =W19/$W$25 -> 0.425 | W19: 17 | Y19: 需要内部推进 | Z19: =AA19/$AA$24 -> 0.3 | AA19: 6
U20: 不做商业化变现 | V20: =W20/$W$25 -> 0.275 | W20: 11 | Y20: CPC结算 | Z20: =AA20/$AA$24 -> 0.3 | AA20: 6
U21: 只与保司合作 | V21: =W21/$W$25 -> 0.15 | W21: 6 | Y21: CPM/CPT结算 | Z21: =AA21/$AA$24 -> 0.15 | AA21: 3
U22: 数据回传问题 | V22: =W22/$W$25 -> 0.05 | W22: 2 | Y22: 流量置换 | Z22: =AA22/$AA$24 -> 0.1 | AA22: 2
U23: 不支持微信支付 | V23: =W23/$W$25 -> 0.025 | W23: 1 | Y23: 待沟通细节 | Z23: =AA23/$AA$24 -> 0.15 | AA23: 3
U24: 测过保险但转化差 | V24: =W24/$W$25 -> 0.075 | W24: 3 | Y24: 合计 | Z24: =SUM(Z19:Z23) -> 1 | AA24: =SUM(AA19:AA23) -> 20
U25: 合计 | V25: =SUM(V19:V24) -> 1 | W25: =SUM(W19:W24) -> 40
